{"article_publication_date": "12-01-1987", "fulltext": "\n\t\t\t", "proc_id": "38765", "abstract": "<p>MELD combines concepts from data flow and object-oriented programming languages in a unique approach to tool reusability. MELD provides three units of abstraction &#8212; equations, classes and features &#8212; that together allow sufficient options for granularity and encapsulation to support the implementation of reusable tools and the composition of existing tools in parallel (<italic>i.e.</italic>, interleaved) as well as in series.</p>", "authors": [{"name": "Gail E. Kaiser", "author_profile_id": "81100462066", "affiliation": "Columbia Univ.", "person_id": "P93522", "email_address": "", "orcid_id": ""}, {"name": "David Garlan", "author_profile_id": "81452615764", "affiliation": "Carnegie-Mellon Univ.", "person_id": "PP39036652", "email_address": "", "orcid_id": ""}], "doi_number": "10.1145/38765.38830", "year": "1987", "article_id": "38830", "conference": "OOPSLA", "title": "MELDing data flow and object-oriented programming", "url": "http://dl.acm.org/citation.cfm?id=38830"}