{"article_publication_date": "01-01-1997", "fulltext": "\n\t\t\t", "proc_id": "274567", "abstract": "", "authors": [{"name": "Richard Jordan", "author_profile_id": "81100368408", "affiliation": "Lucent Technologies, Columbus, OH", "person_id": "PP14131059", "email_address": "", "orcid_id": ""}, {"name": "Mark O'Riordan", "author_profile_id": "81100511646", "affiliation": "Lucent Technologies, Columbus, OH", "person_id": "P190813", "email_address": "", "orcid_id": ""}, {"name": "Tom Williams", "author_profile_id": "81332535585", "affiliation": "Lucent Technologies, Columbus, OH", "person_id": "PP14015532", "email_address": "", "orcid_id": ""}], "doi_number": "10.1145/274567.274575", "year": "1997", "article_id": "274575", "conference": "OOPSLA", "title": "Reflections on the ORB: a look back at our experience building an ORB-based architecture", "url": "http://dl.acm.org/citation.cfm?id=274575"}